lightapi/__init__.py
lightapi/auth.py
lightapi/base_endpoint.py
lightapi/cache.py
lightapi/config.py
lightapi/core.py
lightapi/database.py
lightapi/exceptions.py
lightapi/filters.py
lightapi/handlers.py
lightapi/lightapi.py
lightapi/models.py
lightapi/pagination.py
lightapi/rest.py
lightapi/swagger.py
lightapi-0.1.12.dist-info/METADATA
lightapi-0.1.12.dist-info/WHEEL
lightapi-0.1.12.dist-info/licenses/LICENSE
lightapi-0.1.12.dist-info/RECORD
