Metadata-Version: 2.4
Name: lightapi
Version: 0.1.12
Summary: A lightweight framework for building API endpoints using Python's native libraries.
Project-URL: Repository, https://github.com/henriqueblobato/LightApi
Project-URL: Issues, https://github.com/henriqueblobato/LightApi/issues
Project-URL: Homepage, https://github.com/henriqueblobato/LightApi
Author-email: iklobato <iklobato1@gmail.com>
License: MIT
License-File: LICENSE
Keywords: api,endpoint,framework,lightweight,rest,restful
Classifier: License :: OSI Approved :: MIT License
Classifier: Operating System :: OS Independent
Classifier: Programming Language :: Python :: 3
Classifier: Programming Language :: Python :: 3.8
Classifier: Programming Language :: Python :: 3.9
Classifier: Programming Language :: Python :: 3.10
Classifier: Programming Language :: Python :: 3.11
Classifier: Topic :: Internet :: WWW/HTTP
Classifier: Topic :: Internet :: WWW/HTTP :: HTTP Servers
Classifier: Topic :: Software Development :: Libraries :: Application Frameworks
Requires-Python: >=3.8.1
Requires-Dist: aiohttp<4.0.0,>=3.9.5
Requires-Dist: pyjwt<3.0.0,>=2.8.0
Requires-Dist: pyyaml>=5.1
Requires-Dist: redis<6.0.0,>=5.0.0
Requires-Dist: sqlalchemy<3.0.0,>=2.0.30
Requires-Dist: starlette<1.0.0,>=0.37.0
Requires-Dist: uvicorn<1.0.0,>=0.30.0
Provides-Extra: dev
Requires-Dist: black<24.0.0,>=23.3.0; extra == 'dev'
Requires-Dist: flake8<7.0.0,>=6.0.0; extra == 'dev'
Requires-Dist: isort<6.0.0,>=5.12.0; extra == 'dev'
Requires-Dist: mypy<2.0.0,>=1.3.0; extra == 'dev'
Requires-Dist: pytest<8.0.0,>=7.3.1; extra == 'dev'
Provides-Extra: docs
Requires-Dist: mkdocs-awesome-pages-plugin; extra == 'docs'
Requires-Dist: mkdocs-git-authors-plugin; extra == 'docs'
Requires-Dist: mkdocs-git-committers-plugin-2; extra == 'docs'
Requires-Dist: mkdocs-git-revision-date-localized-plugin; extra == 'docs'
Requires-Dist: mkdocs-glightbox; extra == 'docs'
Requires-Dist: mkdocs-material; extra == 'docs'
Requires-Dist: mkdocstrings[python]; extra == 'docs'
Provides-Extra: test
Requires-Dist: httpx<1.0.0,>=0.27.0; extra == 'test'
Requires-Dist: pyjwt<3.0.0,>=2.8.0; extra == 'test'
Requires-Dist: pytest<8.0.0,>=7.3.1; extra == 'test'
Requires-Dist: redis<6.0.0,>=5.0.0; extra == 'test'
Requires-Dist: starlette<1.0.0,>=0.37.0; extra == 'test'
Requires-Dist: uvicorn<1.0.0,>=0.30.0; extra == 'test'
